[
	{
		"text":"This is the start of something big! You must pick:",
		"choicea":"This is a choice",
		"choiceb":"This is another choice",
		"choicec":"This is another another choice",
		"logica":{
			"text":"This is the start of something big!",
			"choicea":"This is a choice",
			"choiceb":"This is another choice",
			"choicec":"This is another another choice",
		},
		"logicb":{
			"text":"This is the start of something big!",
			"choicea":"This is a choice",
			"choiceb":"This is another choice",
			"choicec":"This is another another choice",
		},
		"logicc":{
			"text":"This is the start of something big!",
			"choicea":"This is a choice",
			"choiceb":"This is another choice",
			"choicec":"This is another another choice",
		}
	}
]